psqlm/Connect.py
psqlm/__init__.py
psqlm-1.0.0.dist-info/LICENSE
psqlm-1.0.0.dist-info/METADATA
psqlm-1.0.0.dist-info/WHEEL
psqlm-1.0.0.dist-info/top_level.txt
psqlm-1.0.0.dist-info/RECORD
