Metadata-Version: 2.1
Name: psqlm
Version: 1.0.0
Summary: 使用Python编写的基于pymysql二次封装模块
Home-page: https://gitee.com/liumou_site/psqlm
Author: 坐公交也用券
Author-email: liumou.site@qq.com
License: UNKNOWN
Platform: UNKNOWN
Classifier: Programming Language :: Python :: 3
Classifier: License :: OSI Approved :: MIT License
Classifier: Operating System :: OS Independent
Requires-Python: >=3.0
License-File: LICENSE
